st_xatadb_connection/__init__.py
st_xatadb_connection-1.0.3.dist-info/LICENSE
st_xatadb_connection-1.0.3.dist-info/METADATA
st_xatadb_connection-1.0.3.dist-info/WHEEL
st_xatadb_connection-1.0.3.dist-info/top_level.txt
st_xatadb_connection-1.0.3.dist-info/RECORD
