Metadata-Version: 2.1
Name: st-xatadb-connection
Version: 1.0.3
Summary: Streamlit Xata Data Base ConnectionAn easy way to connect your Streamlit application to your Xata database.
Home-page: https://github.com/SergioSKA27/st-xatadb-connection
Author: Sergio Demis Lopez Martinez
Author-email: sergioska81@hotmail.com
License: MIT
Keywords: streamlit,xata,connection,integration,database
Classifier: Environment :: Plugins
Classifier: Environment :: Web Environment
Classifier: Intended Audience :: Developers
Classifier: License :: OSI Approved :: MIT License
Classifier: Operating System :: OS Independent
Classifier: Programming Language :: Python
Classifier: Topic :: Software Development :: Libraries :: Python Modules
Classifier: Topic :: Database
Classifier: Topic :: Database :: Front-Ends
Classifier: Topic :: Software Development :: Libraries :: Python Modules
Classifier: Topic :: Software Development :: User Interfaces
License-File: LICENSE
Requires-Dist: streamlit >=1.28
Requires-Dist: xata
